odoo10_addon_crm_deduplicate_filter-10.0.1.0.0.99.dev4-py2.7-nspkg.pth
odoo/addons/crm_deduplicate_filter/README.rst
odoo/addons/crm_deduplicate_filter/__init__.py
odoo/addons/crm_deduplicate_filter/__manifest__.py
odoo/addons/crm_deduplicate_filter/i18n/crm_deduplicate_filter.pot
odoo/addons/crm_deduplicate_filter/i18n/de.po
odoo/addons/crm_deduplicate_filter/i18n/es.po
odoo/addons/crm_deduplicate_filter/i18n/hr.po
odoo/addons/crm_deduplicate_filter/i18n/nl_NL.po
odoo/addons/crm_deduplicate_filter/i18n/sk.po
odoo/addons/crm_deduplicate_filter/i18n/sl.po
odoo/addons/crm_deduplicate_filter/i18n/tr.po
odoo/addons/crm_deduplicate_filter/static/description/icon.png
odoo/addons/crm_deduplicate_filter/static/description/icon.svg
odoo/addons/crm_deduplicate_filter/tests/__init__.py
odoo/addons/crm_deduplicate_filter/tests/test_crm_deduplicate_filter.py
odoo/addons/crm_deduplicate_filter/wizards/__init__.py
odoo/addons/crm_deduplicate_filter/wizards/partner_merge.py
odoo/addons/crm_deduplicate_filter/wizards/partner_merge_view.xml
odoo10_addon_crm_deduplicate_filter-10.0.1.0.0.99.dev4.dist-info/DESCRIPTION.rst
odoo10_addon_crm_deduplicate_filter-10.0.1.0.0.99.dev4.dist-info/METADATA
odoo10_addon_crm_deduplicate_filter-10.0.1.0.0.99.dev4.dist-info/RECORD
odoo10_addon_crm_deduplicate_filter-10.0.1.0.0.99.dev4.dist-info/WHEEL
odoo10_addon_crm_deduplicate_filter-10.0.1.0.0.99.dev4.dist-info/metadata.json
odoo10_addon_crm_deduplicate_filter-10.0.1.0.0.99.dev4.dist-info/namespace_packages.txt
odoo10_addon_crm_deduplicate_filter-10.0.1.0.0.99.dev4.dist-info/top_level.txt
